zmongo.py
zmongo-0.1.0.dist-info/LICENSE
zmongo-0.1.0.dist-info/METADATA
zmongo-0.1.0.dist-info/WHEEL
zmongo-0.1.0.dist-info/top_level.txt
zmongo-0.1.0.dist-info/RECORD
